{
    "monitor_pairs": [
        {
            "from_token": "WFRAX-1",
            "from_address": "0x04ACaF8D2865c0714F79da09645C13FD2888977f",
            "to_token": "cvxFXS-1",
            "to_address": "0xFEEf77d3f69374f66429C91d732A244f074bdf74",
            "amount": 100,
            "provider": "odos"
        },
        {
            "from_token": "WFRAX_fraxtal-252",
            "from_address": "0xFc00000000000000000000000000000000000002",
            "to_token": "cvxFXS_fraxtal-252",
            "to_address": "0xEFb4B26FC242478c9008274F9e81db89Fa6adAB9",
            "amount": 100,
            "provider": "odos"
        },
        {
            "from_token": "WFRAX-1",
            "from_address": "0x04ACaF8D2865c0714F79da09645C13FD2888977f",
            "to_token": "frxUSD",
            "to_address": "0xCAcd6fd266aF91b8AeD52aCCc382b4e165586E29",
            "amount": 1000,
            "provider": "odos"
        },
        {
            "from_token": "WFRAX_fraxtal-252",
            "from_address": "0xFc00000000000000000000000000000000000002",
            "to_token": "frxUSD",
            "to_address": "0xFc00000000000000000000000000000000000001",
            "amount": 1000,
            "provider": "odos"
        },
        {
            "from_token": "frxETH-1",
            "from_address": "0x5E8422345238F34275888049021821E8E08CAa1f",
            "to_token": "frxUSD",
            "to_address": "0xCAcd6fd266aF91b8AeD52aCCc382b4e165586E29",
            "amount": 1,
            "provider": "odos"
        },
        {
            "from_token": "frxETH_fraxtal-252",
            "from_address": "0xFC00000000000000000000000000000000000006",
            "to_token": "frxUSD",
            "to_address": "0xFc00000000000000000000000000000000000001",
            "amount": 1,
            "provider": "odos"
        },
        {
            "from_token": "FXS-1",
            "from_address": "0x3432B6A60D23Ca0dFCa7761B7ab56459D9C964D0",
            "to_token": "WFRAX-1",
            "to_address": "0x04ACaF8D2865c0714F79da09645C13FD2888977f",
            "amount": 10000,
            "provider": "odos"
        },
        {
            "from_token": "WFRAX-1",
            "from_address": "0x04ACaF8D2865c0714F79da09645C13FD2888977f",
            "to_token": "pitchFXS-1",
            "to_address": "0x11EBe21e9d7BF541A18e1E3aC94939018Ce88F0b",
            "amount": 100,
            "provider": "odos"
        }
    ]
}
